stanscofi/__init__.py
stanscofi/datasets.py
stanscofi/models.py
stanscofi/preprocessing.py
stanscofi/training_testing.py
stanscofi/utils.py
stanscofi/validation.py
stanscofi-2.0.1.dist-info/METADATA
stanscofi-2.0.1.dist-info/WHEEL
stanscofi-2.0.1.dist-info/top_level.txt
stanscofi-2.0.1.dist-info/RECORD
