Metadata-Version: 2.1
Name: stanscofi
Version: 2.0.1
Summary: Package for STANdard drug Screening by COllaborative FIltering. Performs benchmarks against datasets and SotA algorithms, and implements training, validation and testing procedures.
Home-page: https://github.com/RECeSS-EU-Project/stanscofi
Author: Clémence Réda
Author-email: recess-project@proton.me
Classifier: Intended Audience :: Science/Research
Classifier: Topic :: Scientific/Engineering
Classifier: Topic :: Scientific/Engineering :: Artificial Intelligence
Classifier: License :: OSI Approved :: MIT License
Requires-Python: >=3.8.5
Requires-Dist: pandas >=1.1.4
Requires-Dist: numpy >=1.19.4
Requires-Dist: scikit-learn >=1.2.2
Requires-Dist: scipy >=1.5.4
Requires-Dist: matplotlib >=3.3.2
Requires-Dist: threadpoolctl >=3.1.0
Requires-Dist: joblib >=1.0.1
Requires-Dist: tqdm >=4.58.0
Requires-Dist: codecarbon >=2.2.2
Requires-Dist: seaborn >=0.11.0
Requires-Dist: cute-ranking >=0.0.3
Requires-Dist: umap-learn >=0.5.3
Requires-Dist: fastcluster >=1.2.6
